{"stats":{"minecraft:broken":{"minecraft:wooden_sword":1,"minecraft:iron_sword":9,"minecraft:golden_pickaxe":1,"minecraft:wooden_hoe":1,"minecraft:bow":2},"minecraft:killed_by":{"minecraft:player":289,"minecraft:creeper":18,"minecraft:ender_dragon":5,"minecraft:skeleton":9},"minecraft:custom":{"minecraft:interact_with_smithing_table":4,"minecraft:mob_kills":219,"minecraft:interact_with_crafting_table":13,"minecraft:open_barrel":8,"minecraft:leave_game":21,"minecraft:time_since_death":90805,"minecraft:climb_one_cm":99094,"minecraft:damage_resisted":134315,"minecraft:sprint_one_cm":2278234,"minecraft:walk_one_cm":2028670,"minecraft:damage_blocked_by_shield":2452,"minecraft:drop":45,"minecraft:talked_to_villager":221,"minecraft:play_time":1079815,"minecraft:deaths":358,"minecraft:sneak_time":49539,"minecraft:walk_under_water_one_cm":8034,"minecraft:boat_one_cm":929536,"minecraft:jump":17980,"minecraft:walk_on_water_one_cm":20395,"minecraft:total_world_time":1079815,"minecraft:interact_with_furnace":20,"minecraft:traded_with_villager":852,"minecraft:pot_flower":2,"minecraft:interact_with_grindstone":2,"minecraft:time_since_rest":90807,"minecraft:damage_taken":205551,"minecraft:open_enderchest":51,"minecraft:damage_absorbed":3982,"minecraft:damage_dealt":37161,"minecraft:player_kills":292,"minecraft:swim_one_cm":21902,"minecraft:fly_one_cm":11372396,"minecraft:open_chest":38,"minecraft:crouch_one_cm":113393,"minecraft:aviate_one_cm":429057,"minecraft:fall_one_cm":1078832,"minecraft:inspect_dispenser":2},"minecraft:crafted":{"minecraft:oak_planks":16,"minecraft:piston":1,"minecraft:stone":6,"minecraft:bookshelf":1,"minecraft:flint_and_steel":1,"minecraft:repeater":2,"minecraft:bow":5,"minecraft:ladder":124,"minecraft:chest":1,"minecraft:end_stone":18,"minecraft:oak_button":2,"minecraft:netherite_scrap":4,"minecraft:dark_oak_planks":76,"minecraft:splash_potion":1,"minecraft:diamond_sword":1,"minecraft:arrow":163,"minecraft:diamond_axe":1,"minecraft:crafting_table":1,"minecraft:iron_sword":7,"minecraft:golden_pickaxe":2,"minecraft:red_wool":1072,"minecraft:enchanted_book":2,"minecraft:air":0,"minecraft:jungle_planks":164,"minecraft:oak_boat":1,"minecraft:oak_chest_boat":1,"minecraft:dark_oak_slab":36,"minecraft:iron_chestplate":4,"minecraft:stick":8,"minecraft:compass":3,"minecraft:iron_ingot":14,"minecraft:iron_pickaxe":6,"minecraft:stone_sword":7,"minecraft:blue_wool":932,"minecraft:gold_ingot":6,"minecraft:redstone_torch":6,"minecraft:netherite_ingot":28,"minecraft:shears":1,"minecraft:carrot_on_a_stick":98},"minecraft:picked_up":{"minecraft:cocoa_beans":15,"minecraft:crafting_table":1,"minecraft:coarse_dirt":1,"minecraft:splash_potion":16,"minecraft:anvil":8,"minecraft:leather_leggings":1,"minecraft:wooden_pickaxe":1,"minecraft:stone_brick_stairs":3,"minecraft:oak_trapdoor":1,"minecraft:smooth_stone_slab":4,"minecraft:poppy":1,"minecraft:sugar_cane":3,"minecraft:raw_iron":19,"minecraft:stone_button":3,"minecraft:redstone":90,"minecraft:stone_sword":1,"minecraft:lime_carpet":1,"minecraft:gold_ingot":349,"minecraft:petrified_oak_slab":3,"minecraft:obsidian":3,"minecraft:snowball":33,"minecraft:white_wool":1,"minecraft:cobblestone":50,"minecraft:cooked_beef":65,"minecraft:jungle_log":51,"minecraft:carrot_on_a_stick":21,"minecraft:flint":1,"minecraft:ancient_debris":9,"minecraft:gunpowder":13,"minecraft:cobblestone_stairs":2,"minecraft:wooden_hoe":1,"minecraft:dirt":25,"minecraft:stone_bricks":3,"minecraft:raw_gold":11,"minecraft:iron_ingot":2080,"minecraft:iron_sword":1,"minecraft:oak_planks":51,"minecraft:dark_oak_stairs":3,"minecraft:book":48,"minecraft:dark_oak_slab":1,"minecraft:chiseled_stone_bricks":2,"minecraft:yellow_concrete":1,"minecraft:stone_brick_slab":16,"minecraft:poisonous_potato":1,"minecraft:gravel":15,"minecraft:sand":18,"minecraft:ink_sac":1,"minecraft:dark_oak_log":21,"minecraft:netherite_block":5,"minecraft:polished_andesite":3,"minecraft:sugar":1,"minecraft:diamond":46,"minecraft:golden_apple":2,"minecraft:emerald":38,"minecraft:coal":15,"minecraft:nether_star":1,"minecraft:ender_pearl":1},"minecraft:dropped":{"minecraft:iron_ingot":13,"minecraft:cooked_beef":64,"minecraft:nether_star":4,"minecraft:diamond":7,"minecraft:crafting_table":1,"minecraft:carrot_on_a_stick":3,"minecraft:stick":1,"minecraft:ink_sac":1,"minecraft:sugar":2,"minecraft:gold_ingot":3,"minecraft:brown_dye":11,"minecraft:oak_planks":7,"minecraft:petrified_oak_slab":3},"minecraft:killed":{"minecraft:skeleton":2,"minecraft:bat":210,"minecraft:ender_dragon":2,"minecraft:player":106,"minecraft:blaze":1},"minecraft:mined":{"minecraft:diamond_ore":15,"minecraft:cobblestone_stairs":3,"minecraft:jungle_leaves":1,"minecraft:dark_oak_log":33,"minecraft:end_stone":6,"minecraft:obsidian":3,"minecraft:purple_terracotta":3,"minecraft:grass_block":7,"minecraft:jungle_log":52,"minecraft:white_concrete":10,"minecraft:coal_block":17,"minecraft:blue_wool":4,"minecraft:chiseled_stone_bricks":3,"minecraft:smooth_stone":2,"minecraft:redstone_ore":20,"minecraft:oak_trapdoor":1,"minecraft:iron_ore":19,"minecraft:fire":5,"minecraft:andesite":1,"minecraft:black_concrete":14,"minecraft:anvil":8,"minecraft:dark_oak_stairs":3,"minecraft:bookshelf":16,"minecraft:vine":5,"minecraft:stone":10,"minecraft:spruce_slab":1,"minecraft:green_bed":3,"minecraft:pink_terracotta":13,"minecraft:netherite_block":5,"minecraft:red_bed":1,"minecraft:red_wool":3,"minecraft:cyan_terracotta":22,"minecraft:snow_block":937,"minecraft:stone_brick_slab":16,"minecraft:short_grass":4,"minecraft:mossy_cobblestone_wall":1,"minecraft:lime_carpet":1,"minecraft:tall_grass":5,"minecraft:cobblestone":52,"minecraft:sugar_cane":2,"minecraft:oak_planks":42,"minecraft:bricks":5,"minecraft:stone_stairs":2,"minecraft:light_blue_terracotta":6,"minecraft:birch_planks":1,"minecraft:coarse_dirt":2,"minecraft:blue_terracotta":3,"minecraft:dark_oak_slab":1,"minecraft:spruce_log":3,"minecraft:stone_brick_stairs":5,"minecraft:smooth_stone_slab":3,"minecraft:coal_ore":15,"minecraft:cocoa":1,"minecraft:gravel":16,"minecraft:sand":18,"minecraft:dirt":9,"minecraft:polished_andesite":18,"minecraft:stone_bricks":19,"minecraft:ancient_debris":9,"minecraft:gold_ore":11},"minecraft:used":{"minecraft:oak_fence":1,"minecraft:moss_carpet":3,"minecraft:nether_brick_fence":30,"minecraft:trident":60,"minecraft:iron_bars":16,"minecraft:red_sand":566,"minecraft:stone_sword":230,"minecraft:stone_shovel":73,"minecraft:carrot_on_a_stick":3901,"minecraft:light_blue_terracotta":90,"minecraft:oak_sign":1,"minecraft:tinted_glass":4,"minecraft:shield":83,"minecraft:iron_sword":639,"minecraft:wooden_shovel":49,"minecraft:polished_blackstone_wall":19,"minecraft:cooked_chicken":12,"minecraft:netherrack":6,"minecraft:iron_chestplate":1,"minecraft:anvil":6,"minecraft:ancient_debris":10,"minecraft:dirt":16,"minecraft:spruce_stairs":1,"minecraft:nether_bricks":9,"minecraft:jungle_planks":146,"minecraft:chainmail_chestplate":2,"minecraft:deepslate_tile_slab":12,"minecraft:nether_brick_slab":13,"minecraft:diamond_helmet":1,"minecraft:spruce_fence":18,"minecraft:snowball":531,"minecraft:waxed_copper_trapdoor":9,"minecraft:polished_deepslate_stairs":3,"minecraft:dark_oak_planks":54,"minecraft:wooden_axe":37,"minecraft:stone_brick_slab":14,"minecraft:waxed_oxidized_copper":7,"minecraft:cyan_terracotta":133,"minecraft:netherite_shovel":980,"minecraft:bricks":32,"minecraft:red_wool":241,"minecraft:iron_block":5,"minecraft:grass_block":5,"minecraft:jungle_log":9,"minecraft:dark_oak_slab":48,"minecraft:iron_boots":2,"minecraft:barrel":2,"minecraft:stone_brick_stairs":2,"minecraft:stone_bricks":34,"minecraft:tripwire_hook":3,"minecraft:blaze_spawn_egg":1,"minecraft:bedrock":84,"minecraft:bow":1223,"minecraft:black_stained_glass":4,"minecraft:soul_soil":10,"minecraft:netherite_pickaxe":107,"minecraft:skeleton_skull":6,"minecraft:cooked_beef":45,"minecraft:pumpkin":5,"minecraft:stripped_spruce_wood":1,"minecraft:mangrove_leaves":9,"minecraft:chiseled_polished_blackstone":3,"minecraft:dark_oak_stairs":9,"minecraft:water_bucket":3,"minecraft:leather_leggings":4,"minecraft:nether_brick_wall":7,"minecraft:diamond_boots":1,"minecraft:cartography_table":1,"minecraft:glass_bottle":1,"minecraft:stone_pickaxe":79,"minecraft:polished_andesite":2,"minecraft:oak_planks":102,"minecraft:wooden_pickaxe":19,"minecraft:ender_pearl":1,"minecraft:blue_wool":250,"minecraft:waxed_oxidized_cut_copper":2,"minecraft:leather_chestplate":2,"minecraft:redstone_block":7,"minecraft:chainmail_helmet":1,"minecraft:chiseled_nether_bricks":3,"minecraft:leather_boots":2,"minecraft:polished_blackstone_bricks":3,"minecraft:dark_oak_trapdoor":26,"minecraft:polished_deepslate_slab":37,"minecraft:pink_concrete":7,"minecraft:golden_apple":74,"minecraft:sand":1,"minecraft:stripped_dark_oak_log":58,"minecraft:crafting_table":1,"minecraft:blast_furnace":4,"minecraft:smooth_red_sandstone":217,"minecraft:crossbow":37,"minecraft:netherite_helmet":1,"minecraft:blackstone_wall":5,"minecraft:dark_oak_fence_gate":4,"minecraft:stone_brick_wall":20,"minecraft:lingering_potion":9,"minecraft:smoker":5,"minecraft:end_stone":18,"minecraft:lightning_rod":1,"minecraft:lever":1,"minecraft:black_concrete":1,"minecraft:dark_prismarine":7,"minecraft:diamond_pickaxe":40,"minecraft:wooden_hoe":142,"minecraft:netherite_block":7,"minecraft:apple":3,"minecraft:firework_rocket":13,"minecraft:diamond_shovel":13,"minecraft:command_block":7,"minecraft:wind_charge":11,"minecraft:iron_pickaxe":6,"minecraft:barrier":49,"minecraft:netherite_axe":71,"minecraft:spore_blossom":4,"minecraft:leather_helmet":1,"minecraft:green_carpet":2,"minecraft:stone_axe":64,"minecraft:chiseled_stone_bricks":1,"minecraft:wooden_sword":497,"minecraft:diamond_sword":3,"minecraft:fishing_rod":13,"minecraft:potion":7,"minecraft:cobblestone":191,"minecraft:white_banner":9,"minecraft:grindstone":3,"minecraft:chainmail_boots":3,"minecraft:stripped_oak_wood":1,"minecraft:bucket":4,"minecraft:chain":6,"minecraft:smooth_stone_slab":7,"minecraft:oak_boat":1,"minecraft:white_concrete":29,"minecraft:cobweb":9,"minecraft:coarse_dirt":1,"minecraft:diamond_leggings":1,"minecraft:golden_pickaxe":201,"minecraft:splash_potion":116,"minecraft:chainmail_leggings":5}},"DataVersion":3953}