{"stats":{"minecraft:custom":{"minecraft:interact_with_crafting_table":28,"minecraft:open_barrel":1,"minecraft:bell_ring":4,"minecraft:leave_game":67,"minecraft:time_since_death":255,"minecraft:damage_blocked_by_shield":700,"minecraft:play_time":3677115,"minecraft:deaths":817,"minecraft:jump":34929,"minecraft:interact_with_furnace":34,"minecraft:play_record":31,"minecraft:traded_with_villager":926,"minecraft:sleep_in_bed":1,"minecraft:damage_dealt":58806,"minecraft:use_cauldron":4,"minecraft:inspect_dispenser":26,"minecraft:horse_one_cm":62670,"minecraft:interact_with_smithing_table":8,"minecraft:interact_with_anvil":7,"minecraft:sneak_time":161950,"minecraft:interact_with_lectern":7,"minecraft:interact_with_blast_furnace":1,"minecraft:total_world_time":3677115,"minecraft:tune_noteblock":112,"minecraft:time_since_rest":256,"minecraft:swim_one_cm":59356,"minecraft:fly_one_cm":51627839,"minecraft:open_chest":73,"minecraft:fall_one_cm":1499227,"minecraft:open_shulker_box":3,"minecraft:damage_resisted":143696,"minecraft:sprint_one_cm":5229694,"minecraft:drop":452,"minecraft:talked_to_villager":262,"minecraft:interact_with_brewingstand":1,"minecraft:walk_on_water_one_cm":120198,"minecraft:interact_with_loom":4,"minecraft:open_enderchest":28,"minecraft:interact_with_beacon":1,"minecraft:player_kills":284,"minecraft:crouch_one_cm":165468,"minecraft:mob_kills":90,"minecraft:fill_cauldron":2,"minecraft:damage_dealt_resisted":100,"minecraft:climb_one_cm":295824,"minecraft:walk_one_cm":3433804,"minecraft:strider_one_cm":116,"minecraft:walk_under_water_one_cm":380162,"minecraft:boat_one_cm":1135125,"minecraft:pot_flower":9,"minecraft:damage_absorbed":2484,"minecraft:damage_taken":434417,"minecraft:minecart_one_cm":1080,"minecraft:aviate_one_cm":148806},"minecraft:crafted":{"minecraft:yellow_wool":36,"minecraft:cooked_mutton":7,"minecraft:glass":7,"minecraft:repeater":1,"minecraft:end_stone":50,"minecraft:cooked_porkchop":6,"minecraft:iron_pickaxe":7,"minecraft:gold_ingot":19,"minecraft:netherite_ingot":1,"minecraft:iron_nugget":64,"minecraft:stone_pickaxe":3,"minecraft:enchanting_table":1,"minecraft:cobblestone":10,"minecraft:iron_leggings":1,"minecraft:oak_planks":72,"minecraft:stone":3,"minecraft:bow":1,"minecraft:iron_boots":1,"minecraft:crafting_table":3,"minecraft:wooden_pickaxe":4,"minecraft:iron_helmet":1,"minecraft:red_wool":1072,"minecraft:iron_chestplate":7,"minecraft:shield":1,"minecraft:stick":24,"minecraft:iron_ingot":54,"minecraft:stone_sword":10,"minecraft:redstone_torch":4,"minecraft:shears":2,"minecraft:furnace":3,"minecraft:glass_pane":16,"minecraft:iron_axe":2,"minecraft:netherite_scrap":9,"minecraft:cooked_beef":5,"minecraft:iron_sword":3,"minecraft:bucket":2,"minecraft:stone_axe":1,"minecraft:air":0,"minecraft:blue_wool":432,"minecraft:carrot_on_a_stick":446},"minecraft:killed":{"minecraft:skeleton":2,"minecraft:tropical_fish":1,"minecraft:cat":1,"minecraft:zombie":5,"minecraft:cow":3,"minecraft:frog":2,"minecraft:ravager":4,"minecraft:spider":1,"minecraft:wither":1,"minecraft:wolf":13,"minecraft:pig":3,"minecraft:creeper":3,"minecraft:sheep":5,"minecraft:mooshroom":4,"minecraft:bat":32,"minecraft:player":200},"minecraft:dropped":{"minecraft:porkchop":3,"minecraft:warden_spawn_egg":1,"minecraft:bubble_coral_fan":64,"minecraft:rail":64,"minecraft:emerald":84,"minecraft:dirt":64,"minecraft:stone_button":1,"minecraft:netherite_boots":2,"minecraft:wooden_sword":1,"minecraft:writable_book":1,"minecraft:sand":65,"minecraft:music_disc_blocks":4,"minecraft:ancient_debris":3,"minecraft:music_disc_chirp":1,"minecraft:detector_rail":64,"minecraft:netherite_sword":8,"minecraft:music_disc_5":2,"minecraft:deepslate_brick_slab":2,"minecraft:oak_planks":64,"minecraft:music_disc_far":1,"minecraft:quartz_bricks":1,"minecraft:salmon":3,"minecraft:acacia_button":22,"minecraft:tipped_arrow":705,"minecraft:skull_banner_pattern":1,"minecraft:ladder":1,"minecraft:glass":64,"minecraft:ghast_tear":6,"minecraft:stone_brick_stairs":2,"minecraft:egg":104,"minecraft:birch_leaves":64,"minecraft:tnt":832,"minecraft:deepslate_brick_wall":1,"minecraft:horn_coral_block":64,"minecraft:netherite_chestplate":2,"minecraft:netherite_helmet":2,"minecraft:barrier":2,"minecraft:command_block":1,"minecraft:music_disc_pigstep":1,"minecraft:polished_blackstone_button":1,"minecraft:cobweb":1,"minecraft:dark_oak_leaves":65,"minecraft:potion":2,"minecraft:string":64,"minecraft:stone_brick_slab":65,"minecraft:pink_tulip":1,"minecraft:player_head":1219,"minecraft:dark_oak_sign":16,"minecraft:smooth_stone_slab":65,"minecraft:structure_block":1,"minecraft:stone_slab":64,"minecraft:light_blue_concrete":1,"minecraft:oak_sign":2,"minecraft:flower_pot":64,"minecraft:powder_snow_bucket":1,"minecraft:spruce_trapdoor":1,"minecraft:spruce_planks":1,"minecraft:fire_coral_block":64,"minecraft:stone_pressure_plate":64,"minecraft:stone_bricks":1,"minecraft:purple_candle":64,"minecraft:stripped_spruce_wood":1,"minecraft:crimson_nylium":1,"minecraft:moss_block":1,"minecraft:dark_oak_stairs":1,"minecraft:oak_log":3,"minecraft:loom":1,"minecraft:nether_star":1,"minecraft:sandstone_slab":1,"minecraft:lantern":64,"minecraft:chest_minecart":1,"minecraft:bedrock":1,"minecraft:carrot_on_a_stick":80,"minecraft:structure_void":1,"minecraft:spruce_leaves":64,"minecraft:cod":1,"minecraft:music_disc_11":1,"minecraft:music_disc_13":2,"minecraft:netherite_scrap":3,"minecraft:ice":1539,"minecraft:cut_sandstone":1,"minecraft:seagrass":320,"minecraft:snowball":134,"minecraft:white_stained_glass_pane":1,"minecraft:jungle_sign":16,"minecraft:black_concrete":2,"minecraft:tropical_fish_spawn_egg":32,"minecraft:gold_ingot":3,"minecraft:gravel":64,"minecraft:spyglass":1,"minecraft:music_disc_otherside":2,"minecraft:chiseled_stone_bricks":1,"minecraft:leather_chestplate":1,"minecraft:trident":1,"minecraft:oak_wood":1,"minecraft:fire_coral_fan":64,"minecraft:iron_bars":2,"minecraft:arrow":65,"minecraft:written_book":34,"minecraft:axolotl_spawn_egg":1,"minecraft:oak_leaves":64,"minecraft:water_bucket":1,"minecraft:oak_slab":1,"minecraft:vine":1,"minecraft:bookshelf":1,"minecraft:yellow_concrete":1,"minecraft:poisonous_potato":1,"minecraft:mangrove_propagule":64,"minecraft:andesite_wall":1,"minecraft:tropical_fish":2,"minecraft:spruce_stairs":1,"minecraft:grass_block":1,"minecraft:stick":3,"minecraft:diorite":64,"minecraft:sculk_catalyst":1,"minecraft:green_dye":74,"minecraft:repeater":1,"minecraft:jungle_leaves":64,"minecraft:wither_rose":3,"minecraft:redstone":1,"minecraft:red_concrete":1,"minecraft:chiseled_quartz_block":2,"minecraft:jukebox":64,"minecraft:stripped_oak_log":1,"minecraft:dolphin_spawn_egg":64,"minecraft:totem_of_undying":5,"minecraft:acacia_leaves":64,"minecraft:red_terracotta":64,"minecraft:netherite_leggings":2,"minecraft:flint_and_steel":1,"minecraft:light":2,"minecraft:quartz_stairs":1,"minecraft:frog_spawn_egg":1,"minecraft:calcite":65,"minecraft:white_stained_glass":1},"minecraft:broken":{"minecraft:iron_sword":1,"minecraft:fishing_rod":1,"minecraft:netherite_helmet":1,"minecraft:golden_pickaxe":1},"minecraft:used":{"minecraft:moss_block":288,"minecraft:orange_dye":1,"minecraft:music_disc_far":1,"minecraft:writable_book":3,"minecraft:smooth_quartz_slab":124,"minecraft:dead_horn_coral_block":22,"minecraft:spruce_slab":170,"minecraft:dispenser":12,"minecraft:ladder":100,"minecraft:black_carpet":19,"minecraft:chest":1,"minecraft:stone":1063,"minecraft:quartz_stairs":130,"minecraft:waxed_weathered_cut_copper_stairs":1,"minecraft:tube_coral":19,"minecraft:soul_sand":173,"minecraft:weathered_copper":1,"minecraft:skeleton_spawn_egg":212,"minecraft:blue_stained_glass":13,"minecraft:orange_wool":2,"minecraft:deepslate_brick_slab":328,"minecraft:snowball":2649,"minecraft:weeping_vines":22,"minecraft:stripped_spruce_log":214,"minecraft:warden_spawn_egg":20,"minecraft:frog_spawn_egg":64,"minecraft:packed_ice":120,"minecraft:honey_block":6,"minecraft:lava_bucket":106,"minecraft:netherite_shovel":1095,"minecraft:stripped_dark_oak_wood":24,"minecraft:quartz_pillar":136,"minecraft:villager_spawn_egg":524,"minecraft:music_disc_pigstep":1,"minecraft:red_wool":530,"minecraft:warped_hyphae":28,"minecraft:grass_block":159,"minecraft:music_disc_chirp":1,"minecraft:dark_oak_leaves":187,"minecraft:dark_oak_slab":22,"minecraft:waxed_weathered_cut_copper":151,"minecraft:dark_oak_button":6,"minecraft:stone_brick_stairs":123,"minecraft:music_disc_stal":1,"minecraft:netherite_boots":4,"minecraft:dolphin_spawn_egg":67,"minecraft:red_stained_glass_pane":27,"minecraft:snow":78,"minecraft:bow":410,"minecraft:oak_sapling":1,"minecraft:furnace":5,"minecraft:mangrove_slab":9,"minecraft:egg":296,"minecraft:end_stone_brick_stairs":187,"minecraft:seagrass":2,"minecraft:deepslate_brick_wall":263,"minecraft:mossy_stone_bricks":91,"minecraft:diorite":6,"minecraft:damaged_anvil":5,"minecraft:end_stone_bricks":1020,"minecraft:spruce_door":21,"minecraft:infested_stone":202,"minecraft:red_stained_glass":51,"minecraft:powered_rail":20,"minecraft:blackstone_stairs":12,"minecraft:wooden_pickaxe":37,"minecraft:leather_chestplate":2,"minecraft:mossy_stone_brick_stairs":10,"minecraft:black_glazed_terracotta":8,"minecraft:purpur_pillar":1,"minecraft:oak_leaves":65,"minecraft:smooth_quartz_stairs":49,"minecraft:golden_apple":10,"minecraft:respawn_anchor":14,"minecraft:glow_berries":51,"minecraft:dark_oak_trapdoor":65,"minecraft:sand":401,"minecraft:blast_furnace":12,"minecraft:blue_ice":130,"minecraft:acacia_leaves":273,"minecraft:netherite_helmet":4,"minecraft:chiseled_quartz_block":43,"minecraft:bamboo_button":3,"minecraft:purple_concrete_powder":35,"minecraft:deepslate_brick_stairs":281,"minecraft:lightning_rod":9,"minecraft:mangrove_door":1,"minecraft:crying_obsidian":12,"minecraft:stripped_bamboo_block":1,"minecraft:deepslate_iron_ore":3,"minecraft:stone_button":23,"minecraft:cyan_carpet":2,"minecraft:verdant_froglight":31,"minecraft:spore_blossom":5,"minecraft:lectern":8,"minecraft:red_terracotta":15,"minecraft:polished_granite":72,"minecraft:flowering_azalea_leaves":4,"minecraft:soul_lantern":9,"minecraft:coal_block":8,"minecraft:nether_wart_block":4,"minecraft:diamond_sword":26,"minecraft:wooden_sword":651,"minecraft:dark_oak_fence":2,"minecraft:bubble_coral_block":7,"minecraft:white_stained_glass":49,"minecraft:green_concrete_powder":28,"minecraft:ice":6,"minecraft:oak_trapdoor":21,"minecraft:polished_blackstone_brick_slab":75,"minecraft:iron_bars":195,"minecraft:stone_sword":139,"minecraft:dead_tube_coral_block":270,"minecraft:dead_bush":22,"minecraft:carved_pumpkin":3,"minecraft:red_concrete":2013,"minecraft:light_gray_carpet":68,"minecraft:silverfish_spawn_egg":2,"minecraft:tinted_glass":28,"minecraft:music_disc_5":7,"minecraft:wither_skeleton_spawn_egg":11,"minecraft:netherrack":1039,"minecraft:bee_spawn_egg":188,"minecraft:orange_stained_glass":28,"minecraft:torch":4,"minecraft:anvil":29,"minecraft:ancient_debris":3,"minecraft:nether_quartz_ore":54,"minecraft:twisting_vines":10,"minecraft:crimson_hyphae":44,"minecraft:stone_stairs":60,"minecraft:dead_tube_coral":4,"minecraft:nether_brick_slab":116,"minecraft:glow_lichen":102,"minecraft:dead_brain_coral_block":266,"minecraft:blue_concrete":90,"minecraft:mud_brick_stairs":28,"minecraft:nether_brick_stairs":7,"minecraft:oak_fence_gate":7,"minecraft:fern":2,"minecraft:small_dripleaf":7,"minecraft:shroomlight":1,"minecraft:mossy_cobblestone_stairs":6,"minecraft:sea_lantern":1,"minecraft:chipped_anvil":1,"minecraft:iron_axe":1,"minecraft:iron_block":113,"minecraft:muddy_mangrove_roots":5,"minecraft:spruce_button":6,"minecraft:slime_block":35,"minecraft:spawner":9,"minecraft:smooth_quartz":65,"minecraft:lime_dye":2,"minecraft:mud_bricks":242,"minecraft:barrel":2,"minecraft:smooth_basalt":20,"minecraft:blaze_spawn_egg":5,"minecraft:diamond_chestplate":1,"minecraft:tripwire_hook":6,"minecraft:basalt":4,"minecraft:purple_concrete":101,"minecraft:glowstone":11,"minecraft:raw_copper_block":7,"minecraft:lime_concrete":4,"minecraft:iron_trapdoor":32,"minecraft:oxidized_copper":1,"minecraft:acacia_wood":9,"minecraft:cobbled_deepslate":82,"minecraft:horn_coral_fan":3,"minecraft:hanging_roots":28,"minecraft:pointed_dripstone":72,"minecraft:calcite":51,"minecraft:water_bucket":52,"minecraft:chiseled_bookshelf":15,"minecraft:nether_brick_wall":36,"minecraft:tube_coral_block":7,"minecraft:sandstone_stairs":34,"minecraft:lime_wool":52,"minecraft:bubble_coral_fan":3,"minecraft:waxed_oxidized_cut_copper":145,"minecraft:cauldron":11,"minecraft:glow_ink_sac":2,"minecraft:deepslate_bricks":1000,"minecraft:cracked_stone_bricks":65,"minecraft:conduit":2,"minecraft:polished_blackstone_bricks":39,"minecraft:gilded_blackstone":22,"minecraft:pink_concrete":176,"minecraft:diamond_block":2,"minecraft:polished_deepslate_slab":6,"minecraft:mossy_cobblestone":51,"minecraft:orange_carpet":24,"minecraft:lime_terracotta":91,"minecraft:rail":13,"minecraft:vine":43,"minecraft:oak_slab":5,"minecraft:tnt":95,"minecraft:crafting_table":8,"minecraft:green_dye":16,"minecraft:sculk_shrieker":2,"minecraft:white_bed":5,"minecraft:campfire":6,"minecraft:fire_coral":13,"minecraft:mangrove_sign":2,"minecraft:mushroom_stem":50,"minecraft:oak_log":61,"minecraft:amethyst_cluster":3,"minecraft:mud":648,"minecraft:dark_prismarine":7,"minecraft:yellow_dye":2,"minecraft:light":181,"minecraft:oak_button":1,"minecraft:iron_pickaxe":208,"minecraft:spruce_pressure_plate":4,"minecraft:leather_helmet":1,"minecraft:spruce_trapdoor":163,"minecraft:music_disc_blocks":2,"minecraft:crimson_nylium":73,"minecraft:chiseled_stone_bricks":4,"minecraft:cobblestone":281,"minecraft:potion":9,"minecraft:cooked_porkchop":1,"minecraft:andesite_stairs":8,"minecraft:sandstone_slab":50,"minecraft:black_candle":15,"minecraft:stripped_oak_log":126,"minecraft:sculk_vein":409,"minecraft:candle":107,"minecraft:jukebox":24,"minecraft:green_stained_glass":5,"minecraft:moss_carpet":111,"minecraft:blue_terracotta":3,"minecraft:polished_deepslate":245,"minecraft:melon":3,"minecraft:oak_sign":71,"minecraft:bone_block":131,"minecraft:carrot_on_a_stick":4943,"minecraft:polished_basalt":425,"minecraft:white_concrete_powder":20,"minecraft:axolotl_spawn_egg":11,"minecraft:decorated_pot":6,"minecraft:shield":8,"minecraft:iron_sword":387,"minecraft:zombie_spawn_egg":24,"minecraft:bubble_coral":2,"minecraft:bell":1,"minecraft:vex_spawn_egg":4,"minecraft:sculk_sensor":24,"minecraft:iron_chestplate":4,"minecraft:debug_stick":33,"minecraft:green_terracotta":27,"minecraft:white_candle":18,"minecraft:spruce_leaves":13,"minecraft:nether_bricks":6,"minecraft:jungle_planks":6,"minecraft:prismarine_brick_stairs":5,"minecraft:deepslate_tile_slab":5,"minecraft:beehive":51,"minecraft:tuff":90,"minecraft:music_disc_11":5,"minecraft:music_disc_13":11,"minecraft:obsidian":216,"minecraft:polished_deepslate_stairs":24,"minecraft:milk_bucket":4,"minecraft:big_dripleaf":2,"minecraft:glass":8,"minecraft:waxed_oxidized_copper":56,"minecraft:cyan_terracotta":20,"minecraft:bricks":61,"minecraft:coal_ore":4,"minecraft:quartz_slab":196,"minecraft:lantern":42,"minecraft:packed_mud":134,"minecraft:polished_blackstone_brick_wall":14,"minecraft:warped_nylium":39,"minecraft:iron_helmet":2,"minecraft:mossy_cobblestone_slab":20,"minecraft:tropical_fish_spawn_egg":59,"minecraft:crimson_roots":5,"minecraft:raw_gold_block":83,"minecraft:stone_bricks":1414,"minecraft:item_frame":2,"minecraft:slime_spawn_egg":7,"minecraft:bedrock":1203,"minecraft:birch_button":3,"minecraft:red_carpet":52,"minecraft:repeater":122,"minecraft:magma_block":193,"minecraft:horn_coral":4,"minecraft:infested_cracked_stone_bricks":193,"minecraft:hay_block":6,"minecraft:written_book":17,"minecraft:mangrove_roots":120,"minecraft:gold_block":43,"minecraft:skeleton_skull":4,"minecraft:fire_coral_fan":2,"minecraft:pearlescent_froglight":389,"minecraft:oak_chest_boat":12,"minecraft:stripped_spruce_wood":147,"minecraft:mangrove_leaves":481,"minecraft:chiseled_polished_blackstone":21,"minecraft:dark_oak_stairs":1,"minecraft:tube_coral_fan":4,"minecraft:end_rod":39,"minecraft:diamond_boots":2,"minecraft:wither_skeleton_skull":20,"minecraft:gray_carpet":5,"minecraft:dark_oak_sign":1,"minecraft:elder_guardian_spawn_egg":59,"minecraft:stone_pickaxe":183,"minecraft:oak_planks":321,"minecraft:mangrove_planks":3,"minecraft:prismarine_stairs":3,"minecraft:birch_wood":26,"minecraft:ender_pearl":5,"minecraft:sandstone":390,"minecraft:end_stone_brick_slab":883,"minecraft:redstone_block":68,"minecraft:structure_void":8,"minecraft:sugar_cane":1,"minecraft:large_amethyst_bud":2,"minecraft:brain_coral":12,"minecraft:white_wool":134,"minecraft:netherite_leggings":3,"minecraft:light_blue_concrete":16,"minecraft:loom":48,"minecraft:yellow_concrete":12,"minecraft:crossbow":25,"minecraft:lingering_potion":54,"minecraft:sponge":152,"minecraft:note_block":18,"minecraft:blackstone_wall":21,"minecraft:ochre_froglight":2,"minecraft:dripstone_block":81,"minecraft:stone_brick_wall":235,"minecraft:end_stone":406,"minecraft:shears":2,"minecraft:cobbled_deepslate_stairs":28,"minecraft:creeper_spawn_egg":45,"minecraft:redstone_torch":10,"minecraft:sticky_piston":29,"minecraft:dead_fire_coral_fan":6,"minecraft:lever":2,"minecraft:green_concrete":39,"minecraft:black_concrete":257,"minecraft:firework_rocket":70,"minecraft:heavy_weighted_pressure_plate":2,"minecraft:string":37,"minecraft:barrier":490,"minecraft:iron_door":42,"minecraft:deepslate":85,"minecraft:gravel":2,"minecraft:blackstone_slab":119,"minecraft:dead_horn_coral":3,"minecraft:jungle_sign":3,"minecraft:chainmail_boots":1,"minecraft:stripped_oak_wood":9,"minecraft:waxed_oxidized_cut_copper_stairs":2,"minecraft:andesite":365,"minecraft:chain":115,"minecraft:mossy_cobblestone_wall":15,"minecraft:smooth_stone_slab":89,"minecraft:chest_minecart":2,"minecraft:white_concrete":30,"minecraft:coarse_dirt":133,"minecraft:bamboo_mosaic_slab":1,"minecraft:bone_meal":45,"minecraft:golden_pickaxe":43,"minecraft:cobweb":57,"minecraft:experience_bottle":19,"minecraft:azalea":22,"minecraft:oak_fence":4,"minecraft:netherite_sword":68,"minecraft:purpur_block":4,"minecraft:petrified_oak_slab":44,"minecraft:jungle_leaves":178,"minecraft:trident":42,"minecraft:music_disc_otherside":1,"minecraft:flint_and_steel":78,"minecraft:cracked_deepslate_bricks":23,"minecraft:stone_shovel":35,"minecraft:redstone":84,"minecraft:pufferfish_spawn_egg":19,"minecraft:zombie_villager_spawn_egg":4,"minecraft:spruce_planks":343,"minecraft:ender_chest":1,"minecraft:sculk":313,"minecraft:deepslate_gold_ore":1,"minecraft:stripped_birch_wood":1,"minecraft:wooden_shovel":46,"minecraft:end_stone_brick_wall":81,"minecraft:dirt":40,"minecraft:spyglass":8,"minecraft:red_nether_brick_slab":81,"minecraft:white_carpet":13,"minecraft:spruce_stairs":73,"minecraft:diamond_helmet":1,"minecraft:oak_wood":50,"minecraft:raw_iron_block":9,"minecraft:spruce_fence":48,"minecraft:light_blue_stained_glass":31,"minecraft:andesite_wall":170,"minecraft:dark_oak_planks":4,"minecraft:ravager_spawn_egg":3,"minecraft:stone_brick_slab":651,"minecraft:wooden_axe":38,"minecraft:bookshelf":226,"minecraft:oak_stairs":15,"minecraft:smooth_sandstone":9,"minecraft:red_candle":26,"minecraft:polished_blackstone_brick_stairs":17,"minecraft:iron_boots":3,"minecraft:crimson_planks":1,"minecraft:black_stained_glass":1,"minecraft:emerald_block":16,"minecraft:soul_soil":18,"minecraft:pitcher_plant":4,"minecraft:wolf_spawn_egg":183,"minecraft:deepslate_tile_stairs":20,"minecraft:white_stained_glass_pane":29,"minecraft:minecart":34,"minecraft:netherite_pickaxe":335,"minecraft:horn_coral_block":34,"minecraft:stone_pressure_plate":6,"minecraft:cooked_beef":11,"minecraft:dead_bubble_coral_block":33,"minecraft:red_dye":9,"minecraft:zombified_piglin_spawn_egg":163,"minecraft:enchanted_golden_apple":9,"minecraft:powder_snow_bucket":270,"minecraft:pumpkin":1,"minecraft:iron_leggings":2,"minecraft:brain_coral_block":36,"minecraft:cobbled_deepslate_wall":18,"minecraft:crimson_hanging_sign":1,"minecraft:quartz_bricks":48,"minecraft:cooked_mutton":1,"minecraft:acacia_boat":2,"minecraft:amethyst_block":156,"minecraft:cobblestone_stairs":10,"minecraft:lodestone":28,"minecraft:snow_block":187,"minecraft:netherite_chestplate":3,"minecraft:glass_bottle":4,"minecraft:polished_andesite":4,"minecraft:mud_brick_slab":128,"minecraft:blue_wool":255,"minecraft:andesite_slab":67,"minecraft:cut_sandstone":115,"minecraft:spruce_sign":1,"minecraft:magenta_stained_glass":312,"minecraft:beacon":1,"minecraft:red_glazed_terracotta":44,"minecraft:polished_blackstone_pressure_plate":1,"minecraft:terracotta":8,"minecraft:stripped_dark_oak_log":62,"minecraft:music_disc_cat":1,"minecraft:dead_fire_coral_block":39,"minecraft:bamboo_block":4,"minecraft:light_gray_concrete_powder":12,"minecraft:brown_glazed_terracotta":11,"minecraft:infested_deepslate":4,"minecraft:infested_stone_bricks":252,"minecraft:dark_oak_door":2,"minecraft:nether_gold_ore":15,"minecraft:purple_stained_glass":585,"minecraft:netherite_block":485,"minecraft:wooden_hoe":41,"minecraft:flower_pot":16,"minecraft:activator_rail":11,"minecraft:black_wool":8,"minecraft:apple":3,"minecraft:command_block":83,"minecraft:gray_candle":4,"minecraft:netherite_axe":128,"minecraft:detector_rail":6,"minecraft:cracked_nether_bricks":1,"minecraft:stone_slab":98,"minecraft:purple_dye":6,"minecraft:stone_axe":15,"minecraft:fishing_rod":109,"minecraft:fire_coral_block":14,"minecraft:cod_spawn_egg":77,"minecraft:crimson_fungus":1,"minecraft:end_crystal":20,"minecraft:cobbled_deepslate_slab":18,"minecraft:mud_brick_wall":1,"minecraft:bucket":16,"minecraft:red_banner":5,"minecraft:magenta_glazed_terracotta":23,"minecraft:polished_blackstone_button":5,"minecraft:wither_rose":2,"minecraft:sea_pickle":4,"minecraft:gray_wool":2,"minecraft:sculk_catalyst":24,"minecraft:smooth_stone":262,"minecraft:splash_potion":212,"minecraft:pillager_spawn_egg":172},"minecraft:killed_by":{"minecraft:ravager":2,"minecraft:vindicator":9,"minecraft:zombie":1,"minecraft:ender_dragon":4,"minecraft:warden":3,"minecraft:creeper":25,"minecraft:player":291,"minecraft:skeleton":5},"minecraft:mined":{"minecraft:obsidian":7,"minecraft:granite":3,"minecraft:coal_block":2,"minecraft:polished_deepslate_slab":2,"minecraft:deepslate_brick_stairs":3,"minecraft:red_bed":2,"minecraft:blue_stained_glass":3,"minecraft:sugar_cane":11,"minecraft:bricks":42,"minecraft:amethyst_block":1,"minecraft:stone_brick_stairs":6,"minecraft:yellow_stained_glass":8,"minecraft:deepslate":35,"minecraft:yellow_terracotta":8,"minecraft:end_stone":10,"minecraft:redstone_ore":23,"minecraft:green_terracotta":1,"minecraft:andesite":1,"minecraft:stone_brick_slab":10,"minecraft:short_grass":2,"minecraft:copper_ore":1,"minecraft:diorite":2,"minecraft:black_stained_glass":6,"minecraft:coarse_dirt":4,"minecraft:stripped_spruce_wood":17,"minecraft:gravel":5,"minecraft:stone_bricks":4,"minecraft:gold_ore":23,"minecraft:cobblestone_stairs":7,"minecraft:sculk_vein":2,"minecraft:dead_horn_coral":5,"minecraft:grass_block":13,"minecraft:white_concrete":8,"minecraft:soul_soil":3,"minecraft:mud_bricks":7,"minecraft:iron_ore":72,"minecraft:dark_oak_stairs":1,"minecraft:green_bed":1,"minecraft:polished_deepslate_stairs":2,"minecraft:cobblestone":49,"minecraft:oak_planks":15,"minecraft:blue_terracotta":3,"minecraft:dark_oak_slab":1,"minecraft:yellow_wool":1,"minecraft:smooth_stone_slab":1,"minecraft:oak_log":18,"minecraft:sand":14,"minecraft:dirt":13,"minecraft:ancient_debris":18,"minecraft:oak_leaves":16,"minecraft:emerald_block":1,"minecraft:diamond_ore":14,"minecraft:tuff":10,"minecraft:white_stained_glass":2,"minecraft:deepslate_brick_slab":2,"minecraft:furnace":3,"minecraft:stripped_spruce_log":2,"minecraft:black_concrete":11,"minecraft:peony":1,"minecraft:bookshelf":10,"minecraft:shroomlight":3,"minecraft:stripped_oak_log":1,"minecraft:stone":106,"minecraft:red_wool":36,"minecraft:snow_block":1069,"minecraft:crafting_table":5,"minecraft:sculk":11,"minecraft:spruce_stairs":1,"minecraft:gray_wool":65,"minecraft:yellow_bed":2,"minecraft:coal_ore":39,"minecraft:cracked_stone_bricks":1,"minecraft:polished_andesite":1},"minecraft:picked_up":{"minecraft:iron_chestplate":2,"minecraft:anvil":1,"minecraft:prismarine_shard":40,"minecraft:diamond_sword":3,"minecraft:wither_rose":10,"minecraft:infested_stone":64,"minecraft:light":1,"minecraft:amethyst_block":1,"minecraft:music_disc_cat":1,"minecraft:string":67,"minecraft:soul_soil":3,"minecraft:cobbled_deepslate":31,"minecraft:written_book":14,"minecraft:music_disc_blocks":3,"minecraft:tropical_fish":5,"minecraft:blaze_rod":2,"minecraft:snowball":105,"minecraft:cooked_beef":71,"minecraft:water_bucket":1,"minecraft:acacia_leaves":64,"minecraft:brown_wool":1,"minecraft:powder_snow_bucket":1,"minecraft:flint":1,"minecraft:polished_andesite":1,"minecraft:blue_terracotta":3,"minecraft:writable_book":1,"minecraft:granite":3,"minecraft:diamond_pickaxe":1,"minecraft:music_disc_5":5,"minecraft:crafting_table":5,"minecraft:coarse_dirt":3,"minecraft:leather_leggings":1,"minecraft:acacia_button":30,"minecraft:flint_and_steel":1,"minecraft:netherite_scrap":3,"minecraft:cracked_stone_bricks":1,"minecraft:music_disc_otherside":1,"minecraft:beef":22,"minecraft:poppy":3,"minecraft:minecart":1,"minecraft:egg":17,"minecraft:black_stained_glass":1,"minecraft:stone":1,"minecraft:oak_door":1,"minecraft:redstone":104,"minecraft:prismarine_crystals":13,"minecraft:peony":1,"minecraft:yellow_terracotta":8,"minecraft:gold_ingot":155,"minecraft:totem_of_undying":6,"minecraft:mutton":22,"minecraft:white_wool":18,"minecraft:stripped_oak_log":1,"minecraft:birch_leaves":64,"minecraft:blackstone_slab":1,"minecraft:oak_log":17,"minecraft:ancient_debris":19,"minecraft:stone_bricks":2,"minecraft:music_disc_far":1,"minecraft:cobweb":1,"minecraft:waxed_weathered_cut_copper_stairs":1,"minecraft:iron_sword":2,"minecraft:dark_oak_stairs":1,"minecraft:red_wool":46,"minecraft:spyglass":1,"minecraft:gravel":4,"minecraft:potion":17,"minecraft:stone_brick_stairs":3,"minecraft:raw_copper":3,"minecraft:smooth_stone_slab":2,"minecraft:iron_leggings":1,"minecraft:oak_sign":1,"minecraft:red_sand":512,"minecraft:dark_oak_leaves":1,"minecraft:iron_boots":1,"minecraft:furnace":4,"minecraft:stick":15,"minecraft:porkchop":12,"minecraft:diorite":1,"minecraft:jungle_chest_boat":1,"minecraft:vine":1,"minecraft:rotten_flesh":19,"minecraft:music_disc_ward":1,"minecraft:deepslate_brick_stairs":3,"minecraft:obsidian":7,"minecraft:cod":14,"minecraft:cobblestone":215,"minecraft:andesite":1,"minecraft:chiseled_quartz_block":2,"minecraft:tuff":10,"minecraft:dirt":28,"minecraft:bone":6,"minecraft:bow":2,"minecraft:wheat_seeds":1,"minecraft:deepslate_brick_slab":6,"minecraft:raw_gold":24,"minecraft:oak_planks":40,"minecraft:music_disc_13":7,"minecraft:cooked_porkchop":9,"minecraft:poisonous_potato":1,"minecraft:sand":15,"minecraft:spectral_arrow":1,"minecraft:jungle_leaves":64,"minecraft:black_concrete":2,"minecraft:diamond":33,"minecraft:netherite_helmet":1,"minecraft:soul_lantern":1,"minecraft:polished_blackstone_button":2,"minecraft:emerald":112,"minecraft:bone_meal":1,"minecraft:golden_apple":1,"minecraft:oak_sapling":2,"minecraft:nether_star":2,"minecraft:oak_leaves":64,"minecraft:splash_potion":69,"minecraft:ladder":1,"minecraft:chest_minecart":2,"minecraft:structure_block":1,"minecraft:wooden_pickaxe":1,"minecraft:shield":1,"minecraft:iron_axe":1,"minecraft:item_frame":2,"minecraft:player_head":4,"minecraft:sugar_cane":22,"minecraft:spruce_trapdoor":1,"minecraft:raw_iron":73,"minecraft:note_block":1,"minecraft:music_disc_11":3,"minecraft:trident":1,"minecraft:stone_pressure_plate":64,"minecraft:arrow":368,"minecraft:saddle":7,"minecraft:wet_sponge":1,"minecraft:netherite_boots":1,"minecraft:salmon":19,"minecraft:leather":12,"minecraft:carrot_on_a_stick":13,"minecraft:music_disc_stal":1,"minecraft:ice":2,"minecraft:gunpowder":24,"minecraft:cobblestone_stairs":7,"minecraft:cooked_mutton":1,"minecraft:iron_ingot":926,"minecraft:music_disc_chirp":1,"minecraft:green_dye":10,"minecraft:book":30,"minecraft:sculk_catalyst":5,"minecraft:oak_slab":1,"minecraft:stone_brick_slab":10,"minecraft:amethyst_shard":4,"minecraft:white_bed":5,"minecraft:iron_helmet":2,"minecraft:acacia_slab":1,"minecraft:red_concrete":1,"minecraft:coal":59}},"DataVersion":3700}